cp2077_extractor/audio_data/__init__.py
cp2077_extractor/audio_data/adverts.py
cp2077_extractor/audio_data/radio_stations.py
cp2077_extractor/cr2w/datatypes/__init__.py
cp2077_extractor/cr2w/datatypes/anim.py
cp2077_extractor/cr2w/datatypes/appearance.py
cp2077_extractor/cr2w/datatypes/base.py
cp2077_extractor/cr2w/datatypes/ent.py
cp2077_extractor/cr2w/datatypes/game.py
cp2077_extractor/cr2w/datatypes/graph.py
cp2077_extractor/cr2w/datatypes/ink.py
cp2077_extractor/cr2w/datatypes/mesh.py
cp2077_extractor/cr2w/datatypes/physics.py
cp2077_extractor/cr2w/datatypes/quest.py
cp2077_extractor/cr2w/datatypes/rend.py
cp2077_extractor/cr2w/datatypes/scn.py
cp2077_extractor/cr2w/datatypes/work.py
cp2077_extractor/cr2w/datatypes/world.py
cp2077_extractor/cr2w/__init__.py
cp2077_extractor/cr2w/enums.py
cp2077_extractor/cr2w/header_structs.py
cp2077_extractor/cr2w/io.py
cp2077_extractor/cr2w/textures.py
cp2077_extractor/cr2w/utils.py
cp2077_extractor/__init__.py
cp2077_extractor/py.typed
cp2077_extractor/radio_dj.py
cp2077_extractor/redarchive_reader.py
cp2077_extractor/track.py
cp2077_extractor/utils.py
cp2077_extractor-0.4.2.dist-info/LICENSE
cp2077_extractor-0.4.2.dist-info/METADATA
cp2077_extractor-0.4.2.dist-info/WHEEL
cp2077_extractor-0.4.2.dist-info/entry_points.txt
cp2077_extractor-0.4.2.dist-info/RECORD
