Metadata-Version: 2.2
Name: cp2077-extractor
Version: 0.4.2
Summary: Work in progress audio/music extractor for Cyberpunk 2077.
Author-email: Dominic Davis-Foster <dominic@davis-foster.co.uk>
License: MIT
Home-page: https://github.com/domdfcoding/cp2077-extractor
Project-URL: Issue Tracker, https://github.com/domdfcoding/cp2077-extractor/issues
Project-URL: Source Code, https://github.com/domdfcoding/cp2077-extractor
Project-URL: Documentation, https://cp2077-extractor.readthedocs.io/en/latest
Platform: Windows
Platform: macOS
Platform: Linux
Classifier: License :: OSI Approved :: MIT License
Classifier: Operating System :: OS Independent
Classifier: Programming Language :: Python
Classifier: Programming Language :: Python :: 3 :: Only
Classifier: Programming Language :: Python :: 3.10
Classifier: Programming Language :: Python :: 3.11
Classifier: Programming Language :: Python :: 3.12
Classifier: Programming Language :: Python :: Implementation :: CPython
Classifier: Typing :: Typed
Requires-Python: >=3.10
Requires-Dist: domdf-python-tools>=3.10.0
Requires-Dist: fnvhash>=0.2.1
Requires-Dist: kraken-decompressor>=0.1.0; platform_machine in "x86_64/AMD64" and sys_platform != "darwin"
Requires-Dist: lameenc>=1.8.1
Requires-Dist: miniaudio>=1.61
Requires-Dist: mutagen>=1.47.0
Requires-Dist: networkx>=3.4.2
Requires-Dist: pillow>=11.0.0
Requires-Dist: regex>=2025.11.3
Requires-Dist: texture2ddecoder>=1.0.5
Requires-Dist: typing-extensions>=4.15.0
Requires-Dist: wem2ogg>=0.1.0
